mongofy/__init__.py
mongofy/py.typed
mongofy/exceptions/__init__.py
mongofy/exceptions/instance.py
mongofy/instances/__init__.py
mongofy/instances/base.py
mongofy/instances/sync_instance.py
mongofy/odm/__init__.py
mongofy/odm/document.py
mongofy-0.1.0a2.dist-info/licenses/LICENSE.md
mongofy-0.1.0a2.dist-info/METADATA
mongofy-0.1.0a2.dist-info/WHEEL
mongofy-0.1.0a2.dist-info/top_level.txt
mongofy-0.1.0a2.dist-info/RECORD
